gsom/GSOM.py
gsom/__init__.py
gsom/visualize.py
pygsom-0.1.0.dist-info/LICENSE
pygsom-0.1.0.dist-info/METADATA
pygsom-0.1.0.dist-info/WHEEL
pygsom-0.1.0.dist-info/top_level.txt
pygsom-0.1.0.dist-info/RECORD
