Metadata-Version: 2.1
Name: pygsom
Version: 0.1.0
Summary: gsom clustering and dimensional reduction algorithm
Home-page: https://bitbucket.org/thimalk/pygsom/src
Author: Thimal Kempitiya
Author-email: t.kempitiya@gmail.com
Classifier: Programming Language :: Python :: 3
Requires-Python: >=3.6
License-File: LICENSE
Requires-Dist: numpy (>=1.17.4)
Requires-Dist: pandas (>=0.25.3)
Requires-Dist: scipy (>=1.4.1)
Requires-Dist: tqdm (>=4.39.0)
Requires-Dist: matplotlib (>=3.1.2)
